lifehash/__init__.py
lifehash/lifehash.py
lifehash-0.0.1.dist-info/LICENSE
lifehash-0.0.1.dist-info/METADATA
lifehash-0.0.1.dist-info/WHEEL
lifehash-0.0.1.dist-info/top_level.txt
lifehash-0.0.1.dist-info/RECORD
