Metadata-Version: 2.1
Name: lifehash
Version: 0.0.1
Summary: LifeHash is a method of unique hash visualization
Home-page: https://github.com/BlockchainCommons/bc-lifehash-python
Author: Bryan Bishop
Author-email: kanzure@gmail.com
Project-URL: Bug Tracker, https://github.com/BlockchainCommons/bc-lifehash-python/issues
Classifier: Programming Language :: Python :: 3
Classifier: License :: OSI Approved :: BSD License
Classifier: Operating System :: OS Independent
Requires-Python: >=3.6
License-File: LICENSE
